cras7h/__init__.py
cras7h/__version__.py
cras7h/_internal_utils.py
cras7h/adapters.py
cras7h/api.py
cras7h/auth.py
cras7h/certs.py
cras7h/compat.py
cras7h/cookies.py
cras7h/exceptions.py
cras7h/help.py
cras7h/hooks.py
cras7h/models.py
cras7h/packages.py
cras7h/sessions.py
cras7h/status_codes.py
cras7h/structures.py
cras7h/utils.py
cras7h-1.0.dist-info/METADATA
cras7h-1.0.dist-info/WHEEL
cras7h-1.0.dist-info/top_level.txt
cras7h-1.0.dist-info/RECORD
